piglr/__init__.py
piglr/error.py
piglr/game.py
piglr/state.py
piglr/version.py
tests/__init__.py
tests/test_pig.py
piglr-0.0.1.dist-info/LICENSE
piglr-0.0.1.dist-info/METADATA
piglr-0.0.1.dist-info/WHEEL
piglr-0.0.1.dist-info/top_level.txt
piglr-0.0.1.dist-info/RECORD
